lbz/__init__.py
lbz/_cfg.py
lbz/authentication.py
lbz/aws_boto3.py
lbz/aws_ssm.py
lbz/collector.py
lbz/configuration.py
lbz/exceptions.py
lbz/handlers.py
lbz/jwt_utils.py
lbz/misc.py
lbz/py.typed
lbz/request.py
lbz/resource.py
lbz/response.py
lbz/router.py
lbz/type_defs.py
lbz/authz/__init__.py
lbz/authz/authorizer.py
lbz/authz/decorators.py
lbz/authz/utils.py
lbz/dev/__init__.py
lbz/dev/server.py
lbz/dev/test.py
lbz/events/__init__.py
lbz/events/api.py
lbz/events/broker.py
lbz/events/enums.py
lbz/events/event.py
lbz/lambdas/__init__.py
lbz/lambdas/broker.py
lbz/lambdas/client.py
lbz/lambdas/enums.py
lbz/lambdas/exceptions.py
lbz/lambdas/response.py
lbz/rest/__init__.py
lbz/rest/api_gateway_event.py
lbz/rest/enums.py
lbz-0.6.7.dist-info/LICENSE
lbz-0.6.7.dist-info/METADATA
lbz-0.6.7.dist-info/WHEEL
lbz-0.6.7.dist-info/top_level.txt
lbz-0.6.7.dist-info/RECORD
