Metadata-Version: 2.1
Name: lbz
Version: 0.6.7
Summary: AWS Lambda REST ToolBox
Home-page: https://github.com/pdyba/lambdalizator
Author: Piotr Dyba
Author-email: piotr.dyba@localbini.com
License: LICENSE
Platform: UNKNOWN
Classifier: Development Status :: 5 - Production/Stable
Classifier: Intended Audience :: Developers
Classifier: License :: OSI Approved :: MIT License
Classifier: Operating System :: OS Independent
Classifier: Programming Language :: Python
Classifier: Programming Language :: Python :: 3.9
Classifier: Programming Language :: Python :: 3.10
Classifier: Programming Language :: Python :: 3.11
Classifier: Programming Language :: Python :: 3.12
Classifier: Topic :: Software Development :: Libraries :: Python Modules
Requires-Python: >=3.9
License-File: LICENSE
Requires-Dist: boto3 <1.41.0,>=1.40.0
Requires-Dist: multidict <6.7.0,>=6.6.0
Requires-Dist: python-jose <3.6.0,>=3.5.0
